MordinezNLP/__init__.py
MordinezNLP/downloaders/Basic.py
MordinezNLP/downloaders/CommonCrawlDownloader.py
MordinezNLP/downloaders/ElasticSearchDownloader.py
MordinezNLP/downloaders/Processors.py
MordinezNLP/downloaders/__init__.py
MordinezNLP/parsers/HTML_Parser.py
MordinezNLP/parsers/__init__.py
MordinezNLP/parsers/process_pdf.py
MordinezNLP/pipelines/PartOfSpeech.py
MordinezNLP/pipelines/__init__.py
MordinezNLP/processors/Basic.py
MordinezNLP/processors/__init__.py
MordinezNLP/tokenizers/SpacyTokenizer.py
MordinezNLP/tokenizers/__init__.py
MordinezNLP/utils/__init__.py
MordinezNLP/utils/ngram_iterator.py
MordinezNLP/utils/pos_replacement_list.py
MordinezNLP/utils/random_string.py
MordinezNLP/utils/token_replacement_list.py
MordinezNLP-0.1.0.dist-info/LICENSE
MordinezNLP-0.1.0.dist-info/METADATA
MordinezNLP-0.1.0.dist-info/WHEEL
MordinezNLP-0.1.0.dist-info/top_level.txt
MordinezNLP-0.1.0.dist-info/RECORD
