Metadata-Version: 2.1
Name: MordinezNLP
Version: 0.1.0
Summary: Powerfull python tool for modern NLP processing
Home-page: https://github.com/BMarcin/MordinezNLP
Author: Marcin Borzymowski
License: MIT
Keywords: NLP text preprocessing cleaning tool
Platform: UNKNOWN
Classifier: Development Status :: 2 - Pre-Alpha
Classifier: Intended Audience :: Developers
Classifier: Intended Audience :: Science/Research
Classifier: Intended Audience :: Education
Classifier: License :: OSI Approved :: MIT License
Classifier: Operating System :: OS Independent
Classifier: Programming Language :: Python :: 3.6
Classifier: Programming Language :: Python :: 3.7
Classifier: Programming Language :: Python :: 3.8
Classifier: Topic :: Scientific/Engineering :: Artificial Intelligence
Requires-Python: >=3.6
License-File: LICENSE
Requires-Dist: clean-text (>=0.3.0)
Requires-Dist: colorama (==0.4.4)
Requires-Dist: elasticsearch (>=7.10.1)
Requires-Dist: pdfplumber (>=0.5.25)
Requires-Dist: requests (>=2.25.1)
Requires-Dist: selectolax (>=0.2.10)
Requires-Dist: spacy (==3.0.1)
Requires-Dist: spacy-legacy (==3.0.1)
Requires-Dist: stanza (==1.1.1)
Requires-Dist: torch (>=1.7.1)
Requires-Dist: tqdm (>=4.50.2)
